z_base_32-0.1.4.dist-info/METADATA
z_base_32-0.1.4.dist-info/WHEEL
z_base_32-0.1.4.dist-info/license_files/LICENSE
zbase32/__init__.py
zbase32/zbase32.cp38-win_amd64.pyd
z_base_32-0.1.4.dist-info/RECORD
