Metadata-Version: 2.1
Name: z-base-32
Version: 0.1.4
Classifier: Programming Language :: Rust
Classifier: Programming Language :: Python :: Implementation :: CPython
Classifier: Programming Language :: Python :: Implementation :: PyPy
License-File: LICENSE
Summary: z-base-32: human-oriented base-32 encoding
Keywords: zbase32,base32,encode,decode,python
Author: Matus Ferech <matus.ferech@gmail.com>
Author-email: Matus Ferech <matus.ferech@gmail.com>
License: MIT
Requires-Python: >=3.7
Project-URL: Source Code, https://github.com/matusf/z-base-32
